ydb/apps/dstool/compile_protos.py
ydb/apps/dstool/main.py
ydb_dstool-0.0.13.dist-info/AUTHORS
ydb_dstool-0.0.13.dist-info/LICENSE
ydb_dstool-0.0.13.dist-info/METADATA
ydb_dstool-0.0.13.dist-info/WHEEL
ydb_dstool-0.0.13.dist-info/entry_points.txt
ydb_dstool-0.0.13.dist-info/top_level.txt
ydb_dstool-0.0.13.dist-info/RECORD
