Metadata-Version: 2.1
Name: ydb-dstool
Version: 0.0.13
Summary: YDB Distributed Storage Administration Tool
Home-page: https://github.com/ydb-platform/ydb/tree/main/ydb/apps/dstool
Author: Yandex LLC
Author-email: ydb@yandex-team.ru
License: Apache 2.0
Classifier: Programming Language :: Python :: 3
Requires-Python: >=3.7
License-File: LICENSE
License-File: AUTHORS
Requires-Dist: packaging
